{"coord":{"lon":-80.1514,"lat":41.6414},"weather":[{"id":601,"main":"Snow","description":"snow","icon":"13d"}],"base":"stations","main":{"temp":274.24,"feels_like":268.55,"temp_min":273.7,"temp_max":276.51,"pressure":1010,"humidity":88},"visibility":10000,"wind":{"speed":7.2,"deg":260,"gust":12.35},"snow":{"1h":0.64},"clouds":{"all":100},"dt":1681841125,"sys":{"type":2,"id":2040697,"country":"US","sunrise":1681814167,"sunset":1681862605},"timezone":-14400,"id":5200644,"name":"Meadville","cod":200}