{"coord":{"lon":-80.1514,"lat":41.6414},"weather":[{"id":601,"main":"Snow","description":"snow","icon":"13n"},{"id":701,"main":"Mist","description":"mist","icon":"50n"}],"base":"stations","main":{"temp":274.51,"feels_like":269.86,"temp_min":273.77,"temp_max":276.12,"pressure":1001,"humidity":95},"visibility":4828,"wind":{"speed":5.14,"deg":220},"snow":{"1h":0.69},"clouds":{"all":100},"dt":1666074132,"sys":{"type":2,"id":2040697,"country":"US","sunrise":1666092954,"sunset":1666132515},"timezone":-14400,"id":5200644,"name":"Meadville","cod":200}