{"coord":{"lon":-80.1525,"lat":41.639},"weather":[{"id":501,"main":"Rain","description":"moderate rain","icon":"10d"},{"id":701,"main":"Mist","description":"mist","icon":"50d"}],"base":"stations","main":{"temp":286.53,"feels_like":286.46,"temp_min":286.16,"temp_max":286.77,"pressure":1005,"humidity":97},"visibility":6437,"wind":{"speed":1.54,"deg":0},"rain":{"1h":1.62},"clouds":{"all":100},"dt":1672854979,"sys":{"type":2,"id":2040697,"country":"US","sunrise":1672836455,"sunset":1672869780},"timezone":-18000,"id":5200644,"name":"Meadville","cod":200}